LICENSE.txt
MANIFEST.in
README.rst
setup.py
compoundpi/__init__.py
compoundpi/cli.py
compoundpi/client.py
compoundpi/cmdline.py
compoundpi/common.py
compoundpi/configparser.py
compoundpi/exc.py
compoundpi/gui.py
compoundpi/ipaddress.py
compoundpi/protocol.py
compoundpi/server.py
compoundpi/terminal.py
compoundpi.egg-info/PKG-INFO
compoundpi.egg-info/SOURCES.txt
compoundpi.egg-info/dependency_links.txt
compoundpi.egg-info/entry_points.txt
compoundpi.egg-info/requires.txt
compoundpi.egg-info/top_level.txt
compoundpi/qt/__init__.py
compoundpi/qt/binding_helper.py
compoundpi/windows/__init__.py
compoundpi/windows/add_dialog.py
compoundpi/windows/add_dialog.ui
compoundpi/windows/capture_dialog.py
compoundpi/windows/capture_dialog.ui
compoundpi/windows/configure_dialog.py
compoundpi/windows/configure_dialog.ui
compoundpi/windows/exception_dialog.py
compoundpi/windows/exception_dialog.ui
compoundpi/windows/find_dialog.py
compoundpi/windows/find_dialog.ui
compoundpi/windows/main_window.py
compoundpi/windows/main_window.ui
compoundpi/windows/progress_dialog.py
compoundpi/windows/progress_dialog.ui
compoundpi/windows/fallback-theme/camera-photo.png
compoundpi/windows/fallback-theme/camera-photo.svg
compoundpi/windows/fallback-theme/dialog-information.png
compoundpi/windows/fallback-theme/dialog-information.svg
compoundpi/windows/fallback-theme/document-save.png
compoundpi/windows/fallback-theme/document-save.svg
compoundpi/windows/fallback-theme/edit-clear.png
compoundpi/windows/fallback-theme/edit-clear.svg
compoundpi/windows/fallback-theme/edit-select-all.png
compoundpi/windows/fallback-theme/edit-select-all.svg
compoundpi/windows/fallback-theme/emblem-favorite.png
compoundpi/windows/fallback-theme/emblem-favorite.svg
compoundpi/windows/fallback-theme/go-bottom.png
compoundpi/windows/fallback-theme/go-bottom.svg
compoundpi/windows/fallback-theme/go-down.png
compoundpi/windows/fallback-theme/go-down.svg
compoundpi/windows/fallback-theme/go-top.png
compoundpi/windows/fallback-theme/go-top.svg
compoundpi/windows/fallback-theme/go-up.png
compoundpi/windows/fallback-theme/go-up.svg
compoundpi/windows/fallback-theme/list-add.png
compoundpi/windows/fallback-theme/list-add.svg
