Metadata-Version: 1.1
Name: compoundpi
Version: 0.4
Summary: A project for controlling multiple Pi camera modules simultaneously
Home-page: http://compoundpi.readthedocs.org/
Author: Dave Hughes
Author-email: dave@waveform.org.uk
License: GNU General Public License v2 or later (GPLv2+)
Keywords: raspberrypi,camera,multi
Platform: A
Platform: L
Platform: L
Classifier: Development Status :: 4 - Beta
Classifier: Environment :: Console
Classifier: Environment :: X11 Applications :: Qt
Classifier: Environment :: No Input/Output (Daemon)
Classifier: Intended Audience :: Science/Research
Classifier: License :: OSI Approved :: GNU General Public License v2 or later (GPLv2+)
Classifier: Operating System :: POSIX
Classifier: Operating System :: Unix
Classifier: Programming Language :: Python :: 2.7
Classifier: Programming Language :: Python :: 3
Classifier: Topic :: Multimedia :: Graphics :: Capture
Classifier: Topic :: Scientific/Engineering
